dexy/__init__.py
dexy/__init__.pyc
dexy/batch.py
dexy/data.py
dexy/doc.py
dexy/exceptions.py
dexy/filter.py
dexy/load_plugins.py
dexy/node.py
dexy/parser.py
dexy/plugin.py
dexy/reporter.py
dexy/storage.py
dexy/template.py
dexy/utils.py
dexy/version.py
dexy/version.pyc
dexy/wrapper.py
dexy/commands/__init__.py
dexy/commands/cite.py
dexy/commands/conf.py
dexy/commands/dirs.py
dexy/commands/env.py
dexy/commands/fcmds.py
dexy/commands/filters.py
dexy/commands/grep.py
dexy/commands/info.py
dexy/commands/it.py
dexy/commands/nodes.py
dexy/commands/parsers.py
dexy/commands/reporters.py
dexy/commands/serve.py
dexy/commands/templates.py
dexy/commands/utils.py
dexy/datas/__init__.py
dexy/datas/et.py
dexy/datas/h5.py
dexy/datas/soup.py
dexy/filters/__init__.py
dexy/filters/ansi.py
dexy/filters/api.py
dexy/filters/archive.py
dexy/filters/asciidoctor.py
dexy/filters/aws.py
dexy/filters/confluence.py
dexy/filters/deprecated.py
dexy/filters/easy.py
dexy/filters/example.py
dexy/filters/filters.yaml
dexy/filters/fluid_html.py
dexy/filters/genipynb.py
dexy/filters/git.py
dexy/filters/id.py
dexy/filters/ipynb.py
dexy/filters/ipynbcasper.py
dexy/filters/java.py
dexy/filters/latex.py
dexy/filters/lyx.py
dexy/filters/md.py
dexy/filters/org.py
dexy/filters/pexp.py
dexy/filters/phantomjs.py
dexy/filters/process.py
dexy/filters/pydoc.py
dexy/filters/pyg.py
dexy/filters/pyn.py
dexy/filters/pyparse.py
dexy/filters/pytest.py
dexy/filters/rst.py
dexy/filters/sanitize.py
dexy/filters/soup.py
dexy/filters/split.py
dexy/filters/standard.py
dexy/filters/sub.py
dexy/filters/templating.py
dexy/filters/templating_plugins.py
dexy/filters/utils.py
dexy/filters/websequence.py
dexy/filters/wordpress.py
dexy/filters/xxml.py
dexy/filters/yamlargs.py
dexy/filters/asciidoctor/asciidoctor.css
dexy/filters/asciidoctor/colony.css
dexy/filters/asciidoctor/foundation-lime.css
dexy/filters/asciidoctor/foundation-potion.css
dexy/filters/asciidoctor/foundation.css
dexy/filters/asciidoctor/github.css
dexy-1.0.17.dist-info/LICENSE
dexy-1.0.17.dist-info/METADATA
dexy-1.0.17.dist-info/WHEEL
dexy-1.0.17.dist-info/entry_points.txt
dexy-1.0.17.dist-info/top_level.txt
dexy-1.0.17.dist-info/RECORD
