Metadata-Version: 2.1
Name: dexy
Version: 1.0.17
Summary: Document Automation
Home-page: http://dexy.it
Author: Ana Nelson
Author-email: ana@ananelson.com
License: UNKNOWN
Platform: UNKNOWN
Classifier: Development Status :: 5 - Production/Stable
Classifier: Environment :: Console
Classifier: Intended Audience :: Developers
Classifier: Intended Audience :: Education
Classifier: Intended Audience :: Financial and Insurance Industry
Classifier: Intended Audience :: Science/Research
Classifier: License :: OSI Approved :: MIT License
Classifier: Topic :: Documentation
Classifier: Topic :: Software Development :: Build Tools
Classifier: Topic :: Software Development :: Code Generators
Classifier: Topic :: Software Development :: Documentation
Classifier: Topic :: Text Processing
Classifier: Topic :: Text Processing :: Markup :: HTML
Classifier: Topic :: Text Processing :: Markup :: LaTeX
Requires-Dist: pexpect
Requires-Dist: BeautifulSoup4
Requires-Dist: PyYAML
Requires-Dist: cashew
Requires-Dist: chardet
Requires-Dist: inflection (>=0.2.0)
Requires-Dist: jinja2
Requires-Dist: ply (>=3.4)
Requires-Dist: pygments
Requires-Dist: python-modargs
Requires-Dist: requests (>=0.10.6)
Requires-Dist: Markdown
Requires-Dist: docutils
